img_processing/__init__.py
img_processing/processing/__init__.py
img_processing/processing/combination.py
img_processing/processing/transformation.py
img_processing/util/__init__.py
img_processing/util/io.py
img_processing/util/plot.py
img_processing-0.0.4.dist-info/METADATA
img_processing-0.0.4.dist-info/WHEEL
img_processing-0.0.4.dist-info/top_level.txt
img_processing-0.0.4.dist-info/RECORD
