Metadata-Version: 2.1
Name: img-processing
Version: 0.0.4
Summary: Project created by Felipe and supported by https://github.com/tiemi for her students in DIO.
Home-page: https://github.com/felipefporto
Author: Felipe Ferreira Porto
Author-email: felipe.porto@fatec.sp.gov.br
Requires-Python: >=3.8
Requires-Dist: matplotlib
Requires-Dist: numpy
Requires-Dist: scikit-image (>=0.16.1)
